[
    {
        "biomarker": "LDL_cholesterol",
        "value": 5.0,
        "predicted_age": 26.0
    },
    {
        "biomarker": "LDL_cholesterol",
        "value": 10.0,
        "predicted_age": 26.0
    },
    {
        "biomarker": "LDL_cholesterol",
        "value": 15.0,
        "predicted_age": 25.0
    },
    {
        "biomarker": "LDL_cholesterol",
        "value": 20.0,
        "predicted_age": 25.0
    },
    {
        "biomarker": "LDL_cholesterol",
        "value": 25.0,
        "predicted_age": 25.0
    },
    {
        "biomarker": "LDL_cholesterol",
        "value": 30.0,
        "predicted_age": 24.0
    },
    {
        "biomarker": "LDL_cholesterol",
        "value": 35.0,
        "predicted_age": 24.0
    },
    {
        "biomarker": "LDL_cholesterol",
        "value": 40.0,
        "predicted_age": 24.0
    },
    {
        "biomarker": "LDL_cholesterol",
        "value": 45.0,
        "predicted_age": 24.0
    },
    {
        "biomarker": "LDL_cholesterol",
        "value": 50.0,
        "predicted_age": 24.0
    },
    {
        "biomarker": "LDL_cholesterol",
        "value": 55.0,
        "predicted_age": 24.0
    },
    {
        "biomarker": "LDL_cholesterol",
        "value": 60.0,
        "predicted_age": 24.0
    },
    {
        "biomarker": "LDL_cholesterol",
        "value": 65.0,
        "predicted_age": 24.0
    },
    {
        "biomarker": "LDL_cholesterol",
        "value": 70.0,
        "predicted_age": 25.0
    },
    {
        "biomarker": "LDL_cholesterol",
        "value": 75.0,
        "predicted_age": 25.0
    },
    {
        "biomarker": "LDL_cholesterol",
        "value": 80.0,
        "predicted_age": 25.0
    },
    {
        "biomarker": "LDL_cholesterol",
        "value": 85.0,
        "predicted_age": 26.0
    },
    {
        "biomarker": "LDL_cholesterol",
        "value": 90.0,
        "predicted_age": 26.0
    },
    {
        "biomarker": "LDL_cholesterol",
        "value": 95.0,
        "predicted_age": 27.0
    },
    {
        "biomarker": "LDL_cholesterol",
        "value": 100.0,
        "predicted_age": 27.0
    }
]